{
    "id": "fd3694ff-77dc-41b9-b8cf-db78b89f8bc5",
    "revision": 0,
    "last_node_id": 54,
    "last_link_id": 111,
    "nodes": [
        {
            "id": 8,
            "type": "VAEDecode",
            "pos": [
                1210,
                190
            ],
            "size": [
                210,
                46
            ],
            "flags": {},
            "order": 11,
            "mode": 0,
            "inputs": [
                {
                    "localized_name": "samples",
                    "name": "samples",
                    "type": "LATENT",
                    "link": 35
                },
                {
                    "localized_name": "vae",
                    "name": "vae",
                    "type": "VAE",
                    "link": 76
                }
            ],
            "outputs": [
                {
                    "localized_name": "IMAGE",
                    "name": "IMAGE",
                    "type": "IMAGE",
                    "slot_index": 0,
                    "links": [
                        56,
                        93
                    ]
                }
            ],
            "properties": {
                "cnr_id": "comfy-core",
                "ver": "0.3.30",
                "Node name for S&R": "VAEDecode"
            },
            "widgets_values": []
        },
        {
            "id": 39,
            "type": "VAELoader",
            "pos": [
                866.3932495117188,
                499.18597412109375
            ],
            "size": [
                306.36004638671875,
                58
            ],
            "flags": {},
            "order": 0,
            "mode": 0,
            "inputs": [
                {
                    "localized_name": "vae_name",
                    "name": "vae_name",
                    "type": "COMBO",
                    "widget": {
                        "name": "vae_name"
                    },
                    "link": null
                }
            ],
            "outputs": [
                {
                    "localized_name": "VAE",
                    "name": "VAE",
                    "type": "VAE",
                    "slot_index": 0,
                    "links": [
                        76,
                        99
                    ]
                }
            ],
            "properties": {
                "cnr_id": "comfy-core",
                "ver": "0.3.30",
                "Node name for S&R": "VAELoader"
            },
            "widgets_values": [
                "wan_2.1_vae.safetensors"
            ]
        },
        {
            "id": 28,
            "type": "SaveAnimatedWEBP",
            "pos": [
                1460,
                190
            ],
            "size": [
                870.8511352539062,
                643.7430419921875
            ],
            "flags": {},
            "order": 12,
            "mode": 0,
            "inputs": [
                {
                    "localized_name": "images",
                    "name": "images",
                    "type": "IMAGE",
                    "link": 56
                },
                {
                    "localized_name": "filename_prefix",
                    "name": "filename_prefix",
                    "type": "STRING",
                    "widget": {
                        "name": "filename_prefix"
                    },
                    "link": null
                },
                {
                    "localized_name": "fps",
                    "name": "fps",
                    "type": "FLOAT",
                    "widget": {
                        "name": "fps"
                    },
                    "link": null
                },
                {
                    "localized_name": "lossless",
                    "name": "lossless",
                    "type": "BOOLEAN",
                    "widget": {
                        "name": "lossless"
                    },
                    "link": null
                },
                {
                    "localized_name": "quality",
                    "name": "quality",
                    "type": "INT",
                    "widget": {
                        "name": "quality"
                    },
                    "link": null
                },
                {
                    "localized_name": "method",
                    "name": "method",
                    "type": "COMBO",
                    "widget": {
                        "name": "method"
                    },
                    "link": null
                }
            ],
            "outputs": [],
            "properties": {
                "cnr_id": "comfy-core",
                "ver": "0.3.30"
            },
            "widgets_values": [
                "ComfyUI",
                16,
                false,
                90,
                "default"
            ]
        },
        {
            "id": 47,
            "type": "SaveWEBM",
            "pos": [
                2367.213134765625,
                193.6114959716797
            ],
            "size": [
                315,
                130
            ],
            "flags": {},
            "order": 13,
            "mode": 4,
            "inputs": [
                {
                    "localized_name": "images",
                    "name": "images",
                    "type": "IMAGE",
                    "link": 93
                },
                {
                    "localized_name": "filename_prefix",
                    "name": "filename_prefix",
                    "type": "STRING",
                    "widget": {
                        "name": "filename_prefix"
                    },
                    "link": null
                },
                {
                    "localized_name": "codec",
                    "name": "codec",
                    "type": "COMBO",
                    "widget": {
                        "name": "codec"
                    },
                    "link": null
                },
                {
                    "localized_name": "fps",
                    "name": "fps",
                    "type": "FLOAT",
                    "widget": {
                        "name": "fps"
                    },
                    "link": null
                },
                {
                    "localized_name": "crf",
                    "name": "crf",
                    "type": "FLOAT",
                    "widget": {
                        "name": "crf"
                    },
                    "link": null
                }
            ],
            "outputs": [],
            "properties": {
                "cnr_id": "comfy-core",
                "ver": "0.3.30",
                "Node name for S&R": "SaveWEBM"
            },
            "widgets_values": [
                "ComfyUI",
                "vp9",
                24,
                32
            ]
        },
        {
            "id": 7,
            "type": "CLIPTextEncode",
            "pos": [
                413,
                389
            ],
            "size": [
                425.27801513671875,
                180.6060791015625
            ],
            "flags": {},
            "order": 7,
            "mode": 0,
            "inputs": [
                {
                    "localized_name": "clip",
                    "name": "clip",
                    "type": "CLIP",
                    "link": 75
                },
                {
                    "localized_name": "text",
                    "name": "text",
                    "type": "STRING",
                    "widget": {
                        "name": "text"
                    },
                    "link": null
                }
            ],
            "outputs": [
                {
                    "localized_name": "CONDITIONING",
                    "name": "CONDITIONING",
                    "type": "CONDITIONING",
                    "slot_index": 0,
                    "links": [
                        98
                    ]
                }
            ],
            "title": "CLIP Text Encode (Negative Prompt)",
            "properties": {
                "cnr_id": "comfy-core",
                "ver": "0.3.30",
                "Node name for S&R": "CLIPTextEncode"
            },
            "widgets_values": [
                "色调艳丽，过曝，静态，细节模糊不清，字幕，风格，作品，画作，画面，静止，整体发灰，最差质量，低质量，JPEG压缩残留，丑陋的，残缺的，多余的手指，画得不好的手部，画得不好的脸部，畸形的，毁容的，形态畸形的肢体，手指融合，静止不动的画面，杂乱的背景，三条腿，背景人很多，倒着走"
            ],
            "color": "#322",
            "bgcolor": "#533"
        },
        {
            "id": 50,
            "type": "WanImageToVideo",
            "pos": [
                673.0507202148438,
                627.272705078125
            ],
            "size": [
                342.5999755859375,
                210
            ],
            "flags": {},
            "order": 9,
            "mode": 0,
            "inputs": [
                {
                    "localized_name": "positive",
                    "name": "positive",
                    "type": "CONDITIONING",
                    "link": 97
                },
                {
                    "localized_name": "negative",
                    "name": "negative",
                    "type": "CONDITIONING",
                    "link": 98
                },
                {
                    "localized_name": "vae",
                    "name": "vae",
                    "type": "VAE",
                    "link": 99
                },
                {
                    "localized_name": "clip_vision_output",
                    "name": "clip_vision_output",
                    "shape": 7,
                    "type": "CLIP_VISION_OUTPUT",
                    "link": 107
                },
                {
                    "localized_name": "start_image",
                    "name": "start_image",
                    "shape": 7,
                    "type": "IMAGE",
                    "link": 106
                },
                {
                    "localized_name": "width",
                    "name": "width",
                    "type": "INT",
                    "widget": {
                        "name": "width"
                    },
                    "link": null
                },
                {
                    "localized_name": "height",
                    "name": "height",
                    "type": "INT",
                    "widget": {
                        "name": "height"
                    },
                    "link": null
                },
                {
                    "localized_name": "length",
                    "name": "length",
                    "type": "INT",
                    "widget": {
                        "name": "length"
                    },
                    "link": null
                },
                {
                    "localized_name": "batch_size",
                    "name": "batch_size",
                    "type": "INT",
                    "widget": {
                        "name": "batch_size"
                    },
                    "link": null
                }
            ],
            "outputs": [
                {
                    "localized_name": "positive",
                    "name": "positive",
                    "type": "CONDITIONING",
                    "slot_index": 0,
                    "links": [
                        101
                    ]
                },
                {
                    "localized_name": "negative",
                    "name": "negative",
                    "type": "CONDITIONING",
                    "slot_index": 1,
                    "links": [
                        102
                    ]
                },
                {
                    "localized_name": "latent",
                    "name": "latent",
                    "type": "LATENT",
                    "slot_index": 2,
                    "links": [
                        103
                    ]
                }
            ],
            "properties": {
                "cnr_id": "comfy-core",
                "ver": "0.3.30",
                "Node name for S&R": "WanImageToVideo"
            },
            "widgets_values": [
                512,
                512,
                33,
                1
            ]
        },
        {
            "id": 6,
            "type": "CLIPTextEncode",
            "pos": [
                415,
                186
            ],
            "size": [
                422.84503173828125,
                164.31304931640625
            ],
            "flags": {},
            "order": 6,
            "mode": 0,
            "inputs": [
                {
                    "localized_name": "clip",
                    "name": "clip",
                    "type": "CLIP",
                    "link": 74
                },
                {
                    "localized_name": "text",
                    "name": "text",
                    "type": "STRING",
                    "widget": {
                        "name": "text"
                    },
                    "link": null
                }
            ],
            "outputs": [
                {
                    "localized_name": "CONDITIONING",
                    "name": "CONDITIONING",
                    "type": "CONDITIONING",
                    "slot_index": 0,
                    "links": [
                        97
                    ]
                }
            ],
            "title": "CLIP Text Encode (Positive Prompt)",
            "properties": {
                "cnr_id": "comfy-core",
                "ver": "0.3.30",
                "Node name for S&R": "CLIPTextEncode"
            },
            "widgets_values": [
                "a cute anime girl with massive fennec ears and a big fluffy tail wearing a maid outfit turning around"
            ],
            "color": "#232",
            "bgcolor": "#353"
        },
        {
            "id": 3,
            "type": "KSampler",
            "pos": [
                863,
                187
            ],
            "size": [
                315,
                262
            ],
            "flags": {},
            "order": 10,
            "mode": 0,
            "inputs": [
                {
                    "localized_name": "model",
                    "name": "model",
                    "type": "MODEL",
                    "link": 111
                },
                {
                    "localized_name": "positive",
                    "name": "positive",
                    "type": "CONDITIONING",
                    "link": 101
                },
                {
                    "localized_name": "negative",
                    "name": "negative",
                    "type": "CONDITIONING",
                    "link": 102
                },
                {
                    "localized_name": "latent_image",
                    "name": "latent_image",
                    "type": "LATENT",
                    "link": 103
                },
                {
                    "localized_name": "seed",
                    "name": "seed",
                    "type": "INT",
                    "widget": {
                        "name": "seed"
                    },
                    "link": null
                },
                {
                    "localized_name": "steps",
                    "name": "steps",
                    "type": "INT",
                    "widget": {
                        "name": "steps"
                    },
                    "link": null
                },
                {
                    "localized_name": "cfg",
                    "name": "cfg",
                    "type": "FLOAT",
                    "widget": {
                        "name": "cfg"
                    },
                    "link": null
                },
                {
                    "localized_name": "sampler_name",
                    "name": "sampler_name",
                    "type": "COMBO",
                    "widget": {
                        "name": "sampler_name"
                    },
                    "link": null
                },
                {
                    "localized_name": "scheduler",
                    "name": "scheduler",
                    "type": "COMBO",
                    "widget": {
                        "name": "scheduler"
                    },
                    "link": null
                },
                {
                    "localized_name": "denoise",
                    "name": "denoise",
                    "type": "FLOAT",
                    "widget": {
                        "name": "denoise"
                    },
                    "link": null
                }
            ],
            "outputs": [
                {
                    "localized_name": "LATENT",
                    "name": "LATENT",
                    "type": "LATENT",
                    "slot_index": 0,
                    "links": [
                        35
                    ]
                }
            ],
            "properties": {
                "cnr_id": "comfy-core",
                "ver": "0.3.30",
                "Node name for S&R": "KSampler"
            },
            "widgets_values": [
                987948718394761,
                "randomize",
                20,
                6,
                "uni_pc",
                "simple",
                1
            ]
        },
        {
            "id": 49,
            "type": "CLIPVisionLoader",
            "pos": [
                20,
                640
            ],
            "size": [
                315,
                58
            ],
            "flags": {},
            "order": 1,
            "mode": 0,
            "inputs": [
                {
                    "localized_name": "clip_name",
                    "name": "clip_name",
                    "type": "COMBO",
                    "widget": {
                        "name": "clip_name"
                    },
                    "link": null
                }
            ],
            "outputs": [
                {
                    "localized_name": "CLIP_VISION",
                    "name": "CLIP_VISION",
                    "type": "CLIP_VISION",
                    "slot_index": 0,
                    "links": [
                        94
                    ]
                }
            ],
            "properties": {
                "cnr_id": "comfy-core",
                "ver": "0.3.30",
                "Node name for S&R": "CLIPVisionLoader"
            },
            "widgets_values": [
                "clip_vision_h.safetensors"
            ]
        },
        {
            "id": 51,
            "type": "CLIPVisionEncode",
            "pos": [
                360,
                640
            ],
            "size": [
                253.60000610351562,
                78
            ],
            "flags": {},
            "order": 5,
            "mode": 0,
            "inputs": [
                {
                    "localized_name": "clip_vision",
                    "name": "clip_vision",
                    "type": "CLIP_VISION",
                    "link": 94
                },
                {
                    "localized_name": "image",
                    "name": "image",
                    "type": "IMAGE",
                    "link": 109
                },
                {
                    "localized_name": "crop",
                    "name": "crop",
                    "type": "COMBO",
                    "widget": {
                        "name": "crop"
                    },
                    "link": null
                }
            ],
            "outputs": [
                {
                    "localized_name": "CLIP_VISION_OUTPUT",
                    "name": "CLIP_VISION_OUTPUT",
                    "type": "CLIP_VISION_OUTPUT",
                    "slot_index": 0,
                    "links": [
                        107
                    ]
                }
            ],
            "properties": {
                "cnr_id": "comfy-core",
                "ver": "0.3.30",
                "Node name for S&R": "CLIPVisionEncode"
            },
            "widgets_values": [
                "none"
            ]
        },
        {
            "id": 52,
            "type": "LoadImage",
            "pos": [
                20,
                760
            ],
            "size": [
                315,
                314
            ],
            "flags": {},
            "order": 2,
            "mode": 0,
            "inputs": [
                {
                    "localized_name": "image",
                    "name": "image",
                    "type": "COMBO",
                    "widget": {
                        "name": "image"
                    },
                    "link": null
                },
                {
                    "localized_name": "choose file to upload",
                    "name": "upload",
                    "type": "IMAGEUPLOAD",
                    "widget": {
                        "name": "upload"
                    },
                    "link": null
                }
            ],
            "outputs": [
                {
                    "localized_name": "IMAGE",
                    "name": "IMAGE",
                    "type": "IMAGE",
                    "slot_index": 0,
                    "links": [
                        106,
                        109
                    ]
                },
                {
                    "localized_name": "MASK",
                    "name": "MASK",
                    "type": "MASK",
                    "slot_index": 1,
                    "links": null
                }
            ],
            "properties": {
                "cnr_id": "comfy-core",
                "ver": "0.3.30",
                "Node name for S&R": "LoadImage"
            },
            "widgets_values": [
                "flux_dev_example.png",
                "image"
            ]
        },
        {
            "id": 38,
            "type": "CLIPLoader",
            "pos": [
                20,
                190
            ],
            "size": [
                390,
                106
            ],
            "flags": {},
            "order": 3,
            "mode": 0,
            "inputs": [
                {
                    "localized_name": "clip_name",
                    "name": "clip_name",
                    "type": "COMBO",
                    "widget": {
                        "name": "clip_name"
                    },
                    "link": null
                },
                {
                    "localized_name": "type",
                    "name": "type",
                    "type": "COMBO",
                    "widget": {
                        "name": "type"
                    },
                    "link": null
                },
                {
                    "localized_name": "device",
                    "name": "device",
                    "shape": 7,
                    "type": "COMBO",
                    "widget": {
                        "name": "device"
                    },
                    "link": null
                }
            ],
            "outputs": [
                {
                    "localized_name": "CLIP",
                    "name": "CLIP",
                    "type": "CLIP",
                    "slot_index": 0,
                    "links": [
                        74,
                        75
                    ]
                }
            ],
            "properties": {
                "cnr_id": "comfy-core",
                "ver": "0.3.30",
                "Node name for S&R": "CLIPLoader"
            },
            "widgets_values": [
                "umt5_xxl_fp8_e4m3fn_scaled.safetensors",
                "wan",
                "default"
            ]
        },
        {
            "id": 54,
            "type": "ModelSamplingSD3",
            "pos": [
                510,
                70
            ],
            "size": [
                315,
                58
            ],
            "flags": {},
            "order": 8,
            "mode": 0,
            "inputs": [
                {
                    "localized_name": "model",
                    "name": "model",
                    "type": "MODEL",
                    "link": 110
                },
                {
                    "localized_name": "shift",
                    "name": "shift",
                    "type": "FLOAT",
                    "widget": {
                        "name": "shift"
                    },
                    "link": null
                }
            ],
            "outputs": [
                {
                    "localized_name": "MODEL",
                    "name": "MODEL",
                    "type": "MODEL",
                    "slot_index": 0,
                    "links": [
                        111
                    ]
                }
            ],
            "properties": {
                "cnr_id": "comfy-core",
                "ver": "0.3.30",
                "Node name for S&R": "ModelSamplingSD3"
            },
            "widgets_values": [
                8
            ]
        },
        {
            "id": 37,
            "type": "UNETLoader",
            "pos": [
                20,
                70
            ],
            "size": [
                346.7470703125,
                82
            ],
            "flags": {},
            "order": 4,
            "mode": 0,
            "inputs": [
                {
                    "localized_name": "unet_name",
                    "name": "unet_name",
                    "type": "COMBO",
                    "widget": {
                        "name": "unet_name"
                    },
                    "link": null
                },
                {
                    "localized_name": "weight_dtype",
                    "name": "weight_dtype",
                    "type": "COMBO",
                    "widget": {
                        "name": "weight_dtype"
                    },
                    "link": null
                }
            ],
            "outputs": [
                {
                    "localized_name": "MODEL",
                    "name": "MODEL",
                    "type": "MODEL",
                    "slot_index": 0,
                    "links": [
                        110
                    ]
                }
            ],
            "properties": {
                "cnr_id": "comfy-core",
                "ver": "0.3.30",
                "Node name for S&R": "UNETLoader"
            },
            "widgets_values": [
                "wan2.1_i2v_480p_14B_fp16.safetensors",
                "fp8_e4m3fn"
            ]
        }
    ],
    "links": [
        [
            35,
            3,
            0,
            8,
            0,
            "LATENT"
        ],
        [
            56,
            8,
            0,
            28,
            0,
            "IMAGE"
        ],
        [
            74,
            38,
            0,
            6,
            0,
            "CLIP"
        ],
        [
            75,
            38,
            0,
            7,
            0,
            "CLIP"
        ],
        [
            76,
            39,
            0,
            8,
            1,
            "VAE"
        ],
        [
            93,
            8,
            0,
            47,
            0,
            "IMAGE"
        ],
        [
            94,
            49,
            0,
            51,
            0,
            "CLIP_VISION"
        ],
        [
            97,
            6,
            0,
            50,
            0,
            "CONDITIONING"
        ],
        [
            98,
            7,
            0,
            50,
            1,
            "CONDITIONING"
        ],
        [
            99,
            39,
            0,
            50,
            2,
            "VAE"
        ],
        [
            101,
            50,
            0,
            3,
            1,
            "CONDITIONING"
        ],
        [
            102,
            50,
            1,
            3,
            2,
            "CONDITIONING"
        ],
        [
            103,
            50,
            2,
            3,
            3,
            "LATENT"
        ],
        [
            106,
            52,
            0,
            50,
            4,
            "IMAGE"
        ],
        [
            107,
            51,
            0,
            50,
            3,
            "CLIP_VISION_OUTPUT"
        ],
        [
            109,
            52,
            0,
            51,
            1,
            "IMAGE"
        ],
        [
            110,
            37,
            0,
            54,
            0,
            "MODEL"
        ],
        [
            111,
            54,
            0,
            3,
            0,
            "MODEL"
        ]
    ],
    "groups": [],
    "config": {},
    "extra": {
        "ds": {
            "scale": 1.2284597357367766,
            "offset": [
                43.50051045787359,
                -19.852247617212413
            ]
        }
    },
    "version": 0.4
}